odoo9_addon_stock_account_deposit-9.0.1.0.0-py2.7-nspkg.pth
odoo9_addon_stock_account_deposit-9.0.1.0.0.dist-info/DESCRIPTION.rst
odoo9_addon_stock_account_deposit-9.0.1.0.0.dist-info/METADATA
odoo9_addon_stock_account_deposit-9.0.1.0.0.dist-info/RECORD
odoo9_addon_stock_account_deposit-9.0.1.0.0.dist-info/WHEEL
odoo9_addon_stock_account_deposit-9.0.1.0.0.dist-info/metadata.json
odoo9_addon_stock_account_deposit-9.0.1.0.0.dist-info/namespace_packages.txt
odoo9_addon_stock_account_deposit-9.0.1.0.0.dist-info/top_level.txt
odoo_addons/stock_account_deposit/README.rst
odoo_addons/stock_account_deposit/__init__.py
odoo_addons/stock_account_deposit/__openerp__.py
odoo_addons/stock_account_deposit/i18n/es.po
odoo_addons/stock_account_deposit/static/description/icon.png
odoo_addons/stock_account_deposit/tests/__init__.py
odoo_addons/stock_account_deposit/tests/test_stock_account_deposit.py
odoo_addons/stock_account_deposit/wizards/__init__.py
odoo_addons/stock_account_deposit/wizards/stock_quant_wizard.py
